edubaseid/__init__.py
edubaseid/analytics.py
edubaseid/auth.py
edubaseid/cli.py
edubaseid/client.py
edubaseid/config.py
edubaseid/exceptions.py
edubaseid/health.py
edubaseid/logging.py
edubaseid/session.py
edubaseid/user.py
edubaseid/utils.py
edubaseid/webhooks.py
edubaseid-1.0.0.dist-info/licenses/LICENSE
edubaseid-1.0.0.dist-info/METADATA
edubaseid-1.0.0.dist-info/WHEEL
edubaseid-1.0.0.dist-info/entry_points.txt
edubaseid-1.0.0.dist-info/top_level.txt
edubaseid-1.0.0.dist-info/RECORD
